rc3/__init__.py
rc3/cli.py
rc3/commands/__init__.py
rc3/commands/cmd_collection.py
rc3/commands/cmd_decode.py
rc3/commands/cmd_environment.py
rc3/commands/cmd_global.py
rc3/commands/cmd_hello.py
rc3/commands/cmd_import.py
rc3/commands/cmd_keyring.py
rc3/commands/cmd_list.py
rc3/commands/cmd_new.py
rc3/commands/cmd_request.py
rc3/commands/cmd_send.py
rc3/commands/cmd_settings.py
rc3/commands/cmd_upgrade.py
rc3/common/__init__.py
rc3/common/config_helper.py
rc3/common/data_helper.py
rc3/common/decorators.py
rc3/common/env_helper.py
rc3/common/file_helper.py
rc3/common/helper_functions.py
rc3/common/inherit_helper.py
rc3/common/json_helper.py
rc3/common/keyring_helper.py
rc3/common/print_helper.py
rc3/common/rc_globals.py
rc3/data/__init__.py
rc3/data/collection/rc-collection.json
rc3/data/collection/environments/.gitignore
rc3/data/collection/environments/dev.defaults
rc3/data/collection/environments/localhost.defaults
rc3/data/collection/examples/example_Auth_Basic.request
rc3/data/collection/examples/example_Auth_Bearer.request
rc3/data/collection/examples/example_Auth_Token.request
rc3/data/collection/examples/example_Extract_JsonPath.request
rc3/data/collection/examples/example_Extract_Regex.request
rc3/data/collection/examples/example_GET.request
rc3/data/collection/examples/example_KitchenSink.request
rc3/data/collection/examples/example_MintOauth2Token.request
rc3/data/collection/examples/example_POST_file.request
rc3/data/collection/examples/example_POST_fixed_content_type.request
rc3/data/collection/examples/example_POST_json.request
rc3/data/collection/examples/example_POST_text-plain.request
rc3/data/collection/examples/example_PromptForInput.request
rc3/data/collection/examples/example_QueryParams.request
rc3/data/collection/examples/example_UseOauth2Token.request
rc3/data/collection/examples/folder.json
rc3/data/collection/greetings-basic/greeting.request
rc3/data/collection/greetings-basic/greetings.request
rc3-0.0.13.dist-info/LICENSE
rc3-0.0.13.dist-info/METADATA
rc3-0.0.13.dist-info/WHEEL
rc3-0.0.13.dist-info/entry_points.txt
rc3-0.0.13.dist-info/top_level.txt
rc3-0.0.13.dist-info/RECORD
