Metadata-Version: 2.1
Name: rc3
Version: 0.0.13
Summary: Rest CLI (rc)
Home-page: https://github.com/gswilcox01/rc3
Author: Gary Wilcox
Author-email: gary@dugan-wilcox.com
License: MIT License
Project-URL: repository, https://github.com/gswilcox01/rc3
Keywords: rest,cli,postman
Classifier: Programming Language :: Python :: 3
Classifier: License :: OSI Approved :: MIT License
Classifier: Operating System :: OS Independent
Requires-Python: >=3.12
License-File: LICENSE
Requires-Dist: click>=8.1
Requires-Dist: requests>=2.31
Requires-Dist: jsonschema
Requires-Dist: jsonpath-ng
Requires-Dist: funcy
Requires-Dist: pkce
Requires-Dist: pyjwt
Requires-Dist: keyring
Provides-Extra: build
Requires-Dist: build; extra == "build"
Requires-Dist: twine; extra == "build"
Provides-Extra: dev
Requires-Dist: pytest; extra == "dev"
Requires-Dist: responses; extra == "dev"
